dbinidicator/core.py
dbinidicator/init.py
dbindicator-0.1.1.dist-info/METADATA
dbindicator-0.1.1.dist-info/WHEEL
dbindicator-0.1.1.dist-info/entry_points.txt
dbindicator-0.1.1.dist-info/top_level.txt
dbindicator-0.1.1.dist-info/RECORD
