Metadata-Version: 2.4
Name: dbindicator
Version: 0.1.1
Summary: A tool that fetches and executes remote base64 code
Author-email: Your Name <you@example.com>
License: MIT
Requires-Python: >=3.8
Requires-Dist: requests
